froide/__init__.py
froide/_local_settings.py
froide/celery.py
froide/local_settings.py
froide/settings.py
froide/urls.py
froide/wsgi.py
froide/account/__init__.py
froide/account/admin.py
froide/account/api_views.py
froide/account/apps.py
froide/account/forms.py
froide/account/hashers.py
froide/account/menu.py
froide/account/middleware.py
froide/account/models.py
froide/account/oauth_urls.py
froide/account/profile_urls.py
froide/account/services.py
froide/account/tests.py
froide/account/urls.py
froide/account/utils.py
froide/account/views.py
froide/account/widgets.py
froide/account/management/__init__.py
froide/account/management/commands/__init__.py
froide/account/management/commands/send_mass_mail.py
froide/account/migrations/0001_initial.py
froide/account/migrations/0002_auto_20150729_0828.py
froide/account/migrations/0003_auto_20160125_2127.py
froide/account/migrations/0004_user_is_trusted.py
froide/account/migrations/0005_user_is_blocked.py
froide/account/migrations/0006_auto_20160902_1845.py
froide/account/migrations/0007_auto_20170912_1032.py
froide/account/migrations/0008_auto_20170912_1036.py
froide/account/migrations/0009_auto_20170912_1041.py
froide/account/migrations/0010_auto_20171011_2152.py
froide/account/migrations/0011_auto_20171106_1503.py
froide/account/migrations/0012_application.py
froide/account/migrations/0013_auto_20180417_1113.py
froide/account/migrations/__init__.py
froide/account/south_migrations/0001_initial.py
froide/account/south_migrations/0002_auto__add_field_profile_private.py
froide/account/south_migrations/0003_auto__add_field_profile_address.py
froide/account/south_migrations/0004_auto__add_field_profile_organization__add_field_profile_organization_u.py
froide/account/south_migrations/0005_auto__add_user__chg_field_profile_user.py
froide/account/south_migrations/0006_auto__add_field_user_organization__add_field_user_organization_url__ad.py
froide-5.0.0.dist-info/METADATA
froide-5.0.0.dist-info/RECORD
froide-5.0.0.dist-info/WHEEL
froide-5.0.0.dist-info/top_level.txt
